tkcommon/__init__.py
tkcommon/config.py
tkcommon/jira.py
tkcommon/logger.py
tkcommon/slack.py
tkcommon/vault.py
tkcommon-1.0.4.dist-info/METADATA
tkcommon-1.0.4.dist-info/WHEEL
tkcommon-1.0.4.dist-info/top_level.txt
tkcommon-1.0.4.dist-info/RECORD
