Metadata-Version: 2.1
Name: tkcommon
Version: 1.0.4
Summary: tkcommon is a collection of small Python functions and classes for building scripts and internal tools.
Home-page: https://bitbucket.org/tekion/tkcommon
Author: Vinoth Kumar
Author-email: vinothkumarj@tekion.com
License: UNKNOWN
Platform: UNKNOWN
Requires-Python: >3.5.2
Requires-Dist: slack-sdk (==3.11.2)
Requires-Dist: jira (==3.0.1)
Requires-Dist: hvac (==0.11.2)
Requires-Dist: PyYAML (==5.4.1)
Requires-Dist: watchtower (==2.0.1)
